[
    {
      "userid": 1,
      "date": "2003 - 05 - 02",
      "url": "https://lh3.googleusercontent.com/yMxtJ3-LqNq1tJ32IBKBltbVWE3kto1smgPYniexyiwSiKDHFWlNyFoi_VYSnW5KtTEGV6ZaM8vP4a2BtGqFaq7TtNc=w640-h400-e365-rj-sc0x00ffffff",
      "title": "Produto 1",
      "productId": 1,
      "quantity": 3
    },
    {
        "userid": 2,
        "date": "2021 - 12 - 10",
        "url": "https://searchengineland.com/wp-content/seloads/2017/04/google-submit-url-in-search-results-1491825318.png",
        "title": "Produto 2",
        "productId": 2,
        "quantity": 3
      },
      {
        "userid": 3,
        "date": "2007 - 12 - 10",
        "url": "https://www.wikihow.com/images/thumb/5/56/Add-Your-URL-to-Google-Step-2.jpg/v4-460px-Add-Your-URL-to-Google-Step-2.jpg.webp",
        "title": "Produto 3",
        "productId": 3,
        "quantity": 3
      },
      {
        "userid": 4,
        "date": "2006 - 12 - 10",
        "url": "http://www.idebrasil.com.br/blog/wp-content/uploads/2019/11/como-organizar-uma-empresa-pequena-4-passos-fundamentais-850x441.jpg",
        "title": "Produto 4",
        "productId": 4,
        "quantity": 3
      },
      {
        "userid": 5,
        "date": "2005 - 12 - 10",
        "url": "teste",
        "title": "Produto 5",
        "productId": 5,
        "quantity": 3
      }
  ]